compyler/__init__.py
compyler/lalr_parser.py
compyler/lexer.py
compyler/parsing_ast.py
compyler/production.py
compyler/token.py
compyler_tools-0.3.dist-info/METADATA
compyler_tools-0.3.dist-info/WHEEL
compyler_tools-0.3.dist-info/top_level.txt
compyler_tools-0.3.dist-info/RECORD
